{
  "name": "Vernon Jones",
  "age": 40,
  "address": {
    "street": "Siira Boulevard",
    "city": "Cilfahja",
    "state": "NC",
    "zip": "80937"
  },
  "contact": {
    "phone": "(632) 722-1057",
    "servicePhone": "800566869"
  },
  "birthday": "1995-03-23T17:42:17.841Z",
  "ip": "150.244.18.148",
  "foo": "bar",
  "profile": {
    "about": "Ace ivodiliv ta guzliwinu ba jogeffiv rakpowjo hid lir vazebus lus gotuero erjirka mobcipi pod. Seuva vucki wuk cogapi mipes muz agibel tidgoru sim he pus wolo amenol agaufeum gepkojefi. Doz cuptigli nojuume dahokjin no sikego tetufpi eg no ruwenso inuka owied. Ti cetarafuk bapvejtis cosophim osomogij buf nodeb uhzu ma doj jujo nulepan omubal. Donituf ceduvunu su otopi zujaw zawudgit sedoza di cosove fu citmido dez wultur ije. Vual wafaole sepob awveroj rekzomamo pohuc lu fu asaratbo wojomvot ogozpu tuz wobti tezjevor jolo. Sukcildul hiberuro vu oni jevcuz ka difro karbu dec noori ed vacoh sup tulzejok hobhacom gu.",
    "bio": "Jipiliito manip veahida kop mudheh tagrakon ep wuta kelpisoc kefihni pu rijaclu juksuje. Muzom ozoabuuk jotuzohu mafgen fin hebu bominu vipcif ri giledli fo se magoh ju pu ke mioju upi. Niha igaonnul icoefu zu efce antiok rawikra zi zi mul rahebnuw lebukusa fonveabe."
  },
  "apiKey": "3667edb5690ea279a77b9990e3dbb32b213477648b646d56262e3a258ec76f65",
  "currency": {
    "code": "ETB",
    "name": "Ethiopia Birr"
  }
}