{
  "name": "Hulda Jenkins",
  "age": 52,
  "address": {
    "street": "Gavan View",
    "city": "Ivobudjij",
    "state": "VA",
    "zip": "25076"
  },
  "contact": {
    "phone": "(360) 979-3163",
    "servicePhone": "800862468"
  },
  "birthday": "1986-07-08T14:59:04.036Z",
  "ip": "32.161.249.49",
  "foo": "bar",
  "profile": {
    "about": "Nunelum tefiwa mibhoeb fo gehiha nopkijdam suc vo fucgag raan uzecigofi kedezbom ap li ju hagic hec. Firojnin upnejcel zucujob duwvab kupkefog ocnoj fipratti kas bip gepid jag kiit ru sasrosoh tonvanwih gec sidfewjap omaed. Rutmali tudapera wud jut totmi nonnacug sen cekisisi copce wa fim comu ticu lasu le za lemdibsaf ni. Azoiw ri wozvi no sas ja gevfev ludibsij jila piba vuvamna wackapson oju.",
    "bio": "Zaiho tilora le afafulan dozdoput ur tufzupa osucut uni hobhevgen zef to agaru odugo. Ginigvo ihhik ser ibema lu uscal awi hamihem hakap mafrukgu surgok uj lup idoci. Gugji ur nisak revapris likur zap er subitmiz je vi ufeefela ig mavkudiz duhmup."
  },
  "apiKey": "632565265979b8c1def8e21587ef08c69b13fe591914040feb5ff33f0c376af0",
  "currency": {
    "code": "UZS",
    "name": "Uzbekistan Som"
  }
}