{
  "name": "Justin Ross",
  "age": 65,
  "address": {
    "street": "Rezze Key",
    "city": "Lorubniz",
    "state": "MD",
    "zip": "85305"
  },
  "contact": {
    "phone": "(854) 448-4649",
    "servicePhone": "800455274"
  },
  "birthday": "2002-12-19T02:18:28.247Z",
  "ip": "120.98.110.64",
  "foo": "bar",
  "profile": {
    "about": "Rilmup wapazbob sij zod soeco waji kilves ruj vi logafiw lu wuro gukoh vibzagov kuricnij jimteme ded. Ve umebin olso rubut kabfigem gajgebwef wow neem cok vagfi nap zef nijozpuh omacoag. Towikik hu ila jadjurut rijluode eflebluj wetwefik nude osiva sezorba it gibdu. Esabupot zolelse gahkoge bokevu lu rip noascu sip pogsacu zisdu sorpeneg nuhtutad. Zeogvi cizo at imowatok puuzilu ul rarka nimi he iwadobo tuk ame wonzonuj wiiweti jig binu ehkeuhu.",
    "bio": "Zijo de ecatipi fefzu ja ipu gaj jihlaple bu polruege wupkeg wiwulkim. Udsu wiwelu mol rozotkah ad luvvadim uc vadho avemeke achasac zera segzoldo mekmaop cut sa ru. Kisha esdugi sivpot er tosfe pijeg burmuk solkeisa beho sek tavrup hot. Tobesizo tejo so uz zomajo san oza zepat siwav ubizebi ge pijsekes soepuv tevnoh wu doetsir. Wugangon jame nuv tulcevkem upnute dobnu biwhiope wuzru leobti gi izavi wuvda dikicki ihna sih."
  },
  "apiKey": "dbbb781f243ed7715bbd439196990557b1433693b32152d41f2c09192954fe44",
  "currency": {
    "code": "SCR",
    "name": "Seychelles Rupee"
  }
}